creosote/__about__.py
creosote/__init__.py
creosote/__main__.py
creosote/cli.py
creosote/config.py
creosote/formatters.py
creosote/models.py
creosote/parsers.py
creosote/py.typed
creosote/resolvers.py
creosote-4.1.0.dist-info/licenses/LICENSE
creosote-4.1.0.dist-info/METADATA
creosote-4.1.0.dist-info/WHEEL
creosote-4.1.0.dist-info/entry_points.txt
creosote-4.1.0.dist-info/top_level.txt
creosote-4.1.0.dist-info/RECORD
