Metadata-Version: 2.4
Name: creosote
Version: 4.1.0
Summary: Identify unused dependencies and avoid a bloated virtual environment.
Author-email: Fredrik Averpil <fredrik.averpil@gmail.com>
Project-URL: Source, https://github.com/fredrikaverpil/creosote
Project-URL: Tracker, https://github.com/fredrikaverpil/creosote/issues
Classifier: License :: OSI Approved :: MIT License
Classifier: Programming Language :: Python
Classifier: Programming Language :: Python :: 3.9
Classifier: Programming Language :: Python :: 3.10
Classifier: Programming Language :: Python :: 3.11
Classifier: Programming Language :: Python :: 3.12
Classifier: Programming Language :: Python :: 3.13
Classifier: Programming Language :: Python :: Implementation :: CPython
Classifier: Programming Language :: Python :: Implementation :: PyPy
Requires-Python: >=3.9
License-File: LICENSE
Requires-Dist: dotty-dict<1.4,>=1.3.1
Requires-Dist: loguru<0.8,>=0.6.0
Requires-Dist: nbconvert<8.0,>=7.16.4
Requires-Dist: nbformat<6.0,>=5.10.4
Requires-Dist: pip-requirements-parser<33.1,>=32.0.1
Requires-Dist: tomli<3.0.0,>=2.1.0; python_version < "3.11"
Requires-Dist: typing-extensions>=4.12.2
Dynamic: license-file
